{
  "video_id": "4034655",
  "title": "Elena Long",
  "duration": "00:00",
  "thumbnail_src": "https://rule34video.com/contents/videos_screenshots/4034000/4034655/preview.jpg",
  "video_src": "https://rule34video.com/get_file/54/c8ea210a876ef1bbc0b51bed6be5d25d811cb21f99/4034000/4034655/4034655_360.mp4/",
  "upload_date": "2025-09-18",
  "tags": [
    "default site keywords",
    "Tags",
    "skadi arknights",
    "seductive",
    "queen aleena hedgehog sonic",
    "nilah league of legends",
    "kula diamond kof",
    "pool table",
    "green skin",
    "lunamist"
  ],
  "page_url": "https://rule34video.com/video/4034655/elena-long/",
  "extracted_at": "2025-09-19T01:31:23.560402",
  "extraction_method": "enhanced_debug",
  "parsed_at": "2025-09-19T01:31:23.618766",
  "page_number": 1000,
  "folder_path": "scraper_downloads\\page_1000\\4034655"
}